README.md
setup.py
sainsburys_recipe_scraper/__init__.py
sainsburys_recipe_scraper.egg-info/PKG-INFO
sainsburys_recipe_scraper.egg-info/SOURCES.txt
sainsburys_recipe_scraper.egg-info/dependency_links.txt
sainsburys_recipe_scraper.egg-info/requires.txt
sainsburys_recipe_scraper.egg-info/top_level.txt